{
  "exchange_modules": [
    {
      "created_at": "2026-01-17T12:00:33.196635+00:00",
      "faculty": "School of Computing",
      "id": 1,
      "nus_course": "CS3244",
      "nus_course_title": "Machine Learning",
      "nus_course_units": 4.0,
      "partner_univ": "Hong Kong Polytechnic University, The",
      "preapproved": true,
      "pu_course": "AMA4680",
      "pu_course_title": "Statistical Machine Learning",
      "pu_course_units": 3.0,
      "updated_at": "2026-01-17T12:00:33.196635+00:00"
    },
    {
      "created_at": "2026-01-17T12:00:33.196635+00:00",
      "faculty": "School of Computing",
      "id": 2,
      "nus_course": "CS3245",
      "nus_course_title": "Information Retrieval",
      "nus_course_units": 4.0,
      "partner_univ": "Hong Kong Polytechnic University, The",
      "preapproved": true,
      "pu_course": "COMP4133",
      "pu_course_title": "Information Retrieval",
      "pu_course_units": 3.0,
      "updated_at": "2026-01-17T12:00:33.196635+00:00"
    },
    {
      "created_at": "2026-01-17T12:00:33.196635+00:00",
      "faculty": "School of Computing",
      "id": 3,
      "nus_course": "CS5228",
      "nus_course_title": "Knowledge Discovery and Data M",
      "nus_course_units": 4.0,
      "partner_univ": "Hong Kong Polytechnic University, The",
      "preapproved": true,
      "pu_course": "COMP4433",
      "pu_course_title": "Data Mining and Data Warehousing",
      "pu_course_units": 3.0,
      "updated_at": "2026-01-17T12:00:33.196635+00:00"
    },
    {
      "created_at": "2026-01-17T12:00:33.196635+00:00",
      "faculty": "School of Computing",
      "id": 4,
      "nus_course": "IS4262",
      "nus_course_title": "Digital Product Management",
      "nus_course_units": 4.0,
      "partner_univ": "Hong Kong Polytechnic University, The",
      "preapproved": true,
      "pu_course": "MM4772",
      "pu_course_title": "Product Management",
      "pu_course_units": 3.0,
      "updated_at": "2026-01-17T12:00:33.196635+00:00"
    },
    {
      "created_at": "2026-01-17T12:00:33.196635+00:00",
      "faculty": "School of Computing",
      "id": 5,
      "nus_course": "BT4301",
      "nus_course_title": "Business Analytics Solutions D",
      "nus_course_units": 4.0,
      "partner_univ": "Hong Kong Polytechnic University, The",
      "preapproved": true,
      "pu_course": "COMP4123",
      "pu_course_title": "Business Process and Workflow Management",
      "pu_course_units": 3.0,
      "updated_at": "2026-01-17T12:00:33.196635+00:00"
    }
  ],
  "module_offerings": [
    {
      "acad_year": "2025-2026",
      "exam_info": {},
      "id": 7254,
      "module_code": "VCU3101",
      "semester_1": true,
      "semester_2": false,
      "special_term_1": false,
      "special_term_2": false
    },
    {
      "acad_year": "2025-2026",
      "exam_info": {},
      "id": 2,
      "module_code": "ABM5002",
      "semester_1": false,
      "semester_2": true,
      "special_term_1": false,
      "special_term_2": false
    },
    {
      "acad_year": "2025-2026",
      "exam_info": {},
      "id": 3,
      "module_code": "ABM5003",
      "semester_1": true,
      "semester_2": false,
      "special_term_1": false,
      "special_term_2": false
    },
    {
      "acad_year": "2025-2026",
      "exam_info": {},
      "id": 5,
      "module_code": "ABM5101",
      "semester_1": true,
      "semester_2": false,
      "special_term_1": false,
      "special_term_2": false
    },
    {
      "acad_year": "2025-2026",
      "exam_info": {},
      "id": 6,
      "module_code": "ABM5102",
      "semester_1": true,
      "semester_2": false,
      "special_term_1": false,
      "special_term_2": false
    }
  ],
  "modules": [
    {
      "attributes": {},
      "corequisite": null,
      "created_at": "2026-01-15T11:11:50.966502+00:00",
      "department": "BIZ Dean's Office",
      "description": "Not Available",
      "embedding": "[0.0104109235,0.0056572044,0.035110805,-0.027646631,-0.015539937,-0.013503621,0.00677961,0.013086628,-0.012412489,-0.017777799,0.038696945,-0.023560101,0.012336041,0.0016505971,0.05787862,-0.019209474,-0.025631165,0.0037286119,0.037390366,0.055654656,0.03611159,-0.00029363253,-0.011397807,0.005372259,0.020335356,-0.041699294,0.051095534,0.013885865,-7.101911e-05,0.016721416,0.02597866,-0.055209864,-0.01591523,-0.025617266,-0.034082223,0.023351604,0.018361589,0.074725136,-0.037362568,-0.003652163,-0.039864525,-0.038696945,0.022865113,0.01662412,-0.0025784064,0.026117658,0.009528289,0.06143696,0.022920713,0.010987764,0.013093579,0.07722709,-0.023282105,0.01945967,-0.031580266,-0.009569988,-0.04011472,-0.02478328,-0.005966474,0.0006971601,0.013357674,-0.01658242,-0.00024368025,0.030384885,0.016054228,-0.01535924,-0.050873138,0.0015472176,-0.010987764,0.01649902,-0.010084279,-0.022726115,0.017458104,-0.019723766,0.04197729,0.0028737762,-0.030968675,-0.014858848,-0.012106695,0.012120595,0.027952427,0.03077408,-0.046258416,-0.009444891,-0.0294397,-0.028313821,-0.07044401,0.017777799,0.029828895,-0.052124117,-0.021391738,-0.066885665,-0.014539154,0.002031103,-0.0473426,-0.019765465,-0.005615505,0.0074711237,0.004903142,0.027646631,-0.004201204,-0.05776742,0.019626468,0.016276624,0.026770948,-0.043923255,-0.00016386519,0.015192443,-0.05676664,0.013044929,-0.078728266,-0.04203289,0.025617266,0.008506656,0.05090094,-0.030023491,0.030329287,-0.030579483,-0.03488841,-0.046897806,-0.059991386,0.015623336,0.012607086,-0.052985903,-0.015470438,0.03605599,-0.011460356,-0.031107673,-0.025269773,-0.010779267,0.025756264,2.7989565e-05,0.026868245,-0.037390366,0.004079581,0.0008096613,-0.052763507,0.020196358,-0.029884495,-0.04486844,0.044951838,-0.02592306,0.039781127,0.013107478,-0.03800196,0.024421886,-0.032080658,-0.008339859,0.00033511463,0.01652682,0.012308242,0.013802466,-0.043450665,-0.049288567,0.055654656,-0.04250548,-0.030245887,0.010542971,-0.006143696,0.0041073803,0.04055951,-0.0070054815,-0.004604297,0.048232183,-0.040781908,0.007971515,0.012725235,-0.002887676,-0.0947964,0.02486668,0.031441268,0.002041528,-0.01537314,0.0026930794,-0.0042637526,0.059324197,0.04478504,-0.06260454,-0.026326153,-0.04781519,0.0080618635,0.005858751,0.015831832,-0.012607086,0.0044548744,0.006143696,0.0103553245,-0.053402897,0.061103366,-0.0026444301,-0.0177639,-0.016068129,0.02717404,0.0080757635,-0.021489035,-0.027730031,0.053486295,0.019167775,-0.020265857,-0.02538097,-0.025742365,-0.03074628,0.01419166,-0.01955697,0.013371574,0.012176194,-0.029050509,-0.005511257,0.0071653286,-0.00022739146,0.078394674,-0.008791601,-0.00038875904,0.0012926781,-0.017291307,0.009945282,0.018472787,-0.032775644,0.009333692,0.0150534455,-0.019181674,-0.0019442296,-0.00083528896,0.07177839,0.027201839,0.011919049,-0.0048336433,0.013795516,-0.024102192,-0.02126664,0.0115576545,0.024533086,0.04361746,0.0048683924,0.016151527,0.012064996,0.0236296,-0.053625293,-0.0035044781,-0.025811862,-0.07011041,0.016248824,0.0093197925,0.0007280002,-0.0039753327,-0.00265833,-0.018000195,-0.046981204,-0.009097396,-0.01300323,-0.001397795,0.057100233,0.009118246,-0.047064602,0.008360708,0.03183046,-0.015526037,0.040531714,0.02428289,-0.0236157,0.0030822728,0.0006511171,-0.0006754417,0.080618635,-0.04200509,0.01948747,0.0045139487,-0.018889781,-0.012697435,-0.008520556,0.010278876,-0.037529364,0.028286021,0.045229834,-0.030857477,-0.04773179,-0.029022709,0.030079091,-0.010209377,0.04250548,-0.017902898,-0.0005790121,-0.007950665,0.038808145,-0.00502129,0.018820282,0.028828112,-0.013656518,-0.053514093,-0.006734436,0.009722886,-0.023907594,-0.012454189,-0.056460842,0.008694303,-0.02301801,0.012481988,-0.0027556284,0.016693618,0.05679444,0.026381753,0.02483888,0.017861197,-0.025603367,-0.02829992,0.0237269,0.039252937,0.006866484,0.06599608,-0.036389586,0.0010555134,-0.023393303,0.0008509262,-0.017360806,0.0118009,-0.029217305,-0.0005438283,-0.017749999,0.06460611,-0.034721613,0.029634299,-0.037612762,-0.0033950175,-0.0532083,0.02599256,0.0055390564,0.0038224354,-0.028494518,0.01122406,-0.02244812,-0.041143302,-0.017402506,0.025241973,-0.028286021,-0.034721613,-0.03616719,0.020488253,0.014775449,-0.047064602,0.00947269,0.022072826,-0.028258221,-0.007269577,-0.0043958006,0.0037911609,-0.028063625,-0.028633514,-0.011905149,0.047370397,0.00041786168,-0.03616719,-0.012210943,0.031635866,0.016290525,0.05423688,-0.057600625,0.037501566,0.0018921054,-0.004861443,0.028744712,-0.044117853,0.0014038762,0.0045139487,-5.2721374e-05,0.021794831,0.051651526,-0.025533868,-0.047592793,-0.027048942,-0.055988252,0.055376664,-0.030357085,-0.015303641,0.013093579,-0.03427682,0.0032925068,0.018083595,0.052346513,0.0012170981,-0.004003132,0.041671496,-0.04256108,0.0413101,-0.048788175,0.046314016,0.041532498,0.02059945,0.022906812,0.014636452,-0.010723668,0.007950665,-0.022003327,0.03964213,0.001860831,-0.012238743,0.03474941,0.08000705,-0.0037737861,0.029578699,-0.013746867,-0.056989037,0.016888214,0.015470438,0.062270947,0.010077329,-0.01827819,0.0412545,-0.0353332,-0.0064599155,-0.008451057,0.012252643,-0.07922866,0.020404855,-0.021516835,-0.0055877054,-0.04317267,-0.00471897,-0.0029519624,-0.007644871,0.015234143,-0.043895457,-0.029662099,-0.031135473,-0.0354722,0.024394087,-0.0023612226,-0.035027407,-0.016651917,-0.03180266,-0.02244812,-0.051067736,0.037195772,-0.02885591,0.044090055,-0.036723178,0.022323022,-0.031441268,-0.090014875,0.004962216,0.035361003,0.043534063,0.04489624,-0.021072043,0.0053097103,-0.03905834,0.02885591,-0.012336041,0.02893931,0.0022847739,-0.014525254,0.00472592,-0.018166993,-0.030468285,0.055682458,-0.039308533,0.0068873335,0.032970242,-0.037473764,-0.04356186,-0.018153092,0.012183144,0.004482674,0.022156226,0.016665818,-0.04261668,0.027646631,0.03711237,0.029606499,0.023810297,-0.037584964,-0.008458007,0.02713234,0.015206343,-0.047009002,0.0032942442,0.012301291,-0.026159357,0.0069603072,-0.026520751,-0.012447239,-0.033415034,0.012252643,-0.015817933,0.014330657,0.0048023686,0.057656225,-0.0412823,-0.052346513,-0.0294675,-0.048621375,-0.011717502,0.00414213,-0.0066649374,-0.015526037,-0.04598042,-0.034554817,-0.00032164925,-0.009076546,-0.002303886,-0.013698218,0.011342208,-0.038252153,-0.03249765,0.01834769,0.06766406,0.015526037,-0.016082028,-0.051151134,0.00621667,0.008916699,-0.004948316,0.0021631508,-0.04497964,-0.0056815287,0.018750783,-0.018180892,-0.008659554,0.026743148,-0.02303191,-0.012078895,-0.023240406,-0.014817149,-0.03252545,0.0025836187,-0.0057996768,-0.023435004,-0.032247454,-0.06783085,-0.018542286,-0.023268206,-0.010820967,0.0022135375,0.006685787,0.04203289,-0.004962216,-0.051623724,0.019139975,0.008068813,-0.027271338,0.019723766,0.030996475,0.023810297,-0.011251859,-0.012169244,-0.0074016247,-0.032692246,-0.026965544,0.0071236296,0.00068021973,0.00309791,-0.010132928,-0.016332224,0.010890465,-0.017166208,0.014525254,0.043951057,-0.018736882,-0.0651621,0.010153778,-0.020029562,0.018570086,-0.010932165,0.0236713,-0.0023542726,0.025853563,0.01825039,0.007304326,-0.01825039,0.02072455,-0.0051985118,-0.044757243,0.013732968,-0.019834964,0.012579287,0.011925998,0.016360022,-0.0061089466,0.03833555,0.0022691365,-0.034638215,-0.00070280686,-0.01827819,0.020585552,0.026367854,-0.04067071,0.024755482,0.00041916477,-0.011759201,-0.013253425,0.008173062,-0.010403974,0.036361784,0.012266543,-0.008958398,0.009827133,-0.017833399,0.031524666,0.024129992,-0.004020507,-0.013246476,0.027785629,-0.023309905,0.014358457,-0.03591699,-0.009000097,0.0012918094,0.01718011,0.006564164,-0.023087509,0.029106107,0.009000097,0.032970242,0.0008965348,-0.06716366,-0.014441855,0.01476155,-0.038752545,-0.004917042,0.014678151,0.005264536,0.04297807,0.0044618244,0.0236991,-0.002156201,0.041532498,-0.0051811375,-0.014497454,0.004427075,-0.01948747,-0.014136061,-0.010306676,0.002743466,0.0027330413,-0.0032038956,0.037334766,-0.016346123,-0.027577134,0.027021142,-0.015734533,0.0012935469,0.008423258,0.026465151,0.004663371,-0.033442833,0.023337705,0.0029728122,0.014650352,0.0052471613,0.0010859191,-0.016790915,-0.024505286,0.004190779,0.023990994,0.022656616,0.026256656,0.010431773,-0.017944597,-0.015122944,-0.0116132535,-0.0088611,-0.0017843823,0.01471985,-0.0007397281,-0.032052856,-0.001283122,0.019390171,-0.0412823,-0.0177222,-0.040420517,0.042283084,-0.0237269,0.009396241,-0.014143011,-0.029272905,-0.04069851,-0.030996475,0.032886844,-0.021238841,-0.026854346,-0.020738449,0.0011528117,-0.013871965,-0.016957713,-0.03135787,0.007443324,0.0038641347,0.01118236,0.0061193714,-0.0023785972,0.00829121,0.018417189,0.0023646974,0.011578504,0.0055077816,0.019167775,-0.010376174,0.024672082,0.025575567,0.008471906,-0.1358841,0.0020571651,0.025130775,0.017527603,0.036973376,0.011766151,-0.0020606401,-0.029078308,-0.013997063,0.012176194,-0.026201056,0.032219656,-0.007029806,-0.034582615,0.017652702,-0.0236018,0.0024758957,-0.02602036,-0.025533868,0.017555403,0.010091229,0.004489624,0.03188606,-0.011363057,-0.01303798,-0.04609162,-0.01063332,0.025561668,0.006671887,-0.009576938,-0.02891151,0.0034419291,0.0412545,-0.015345341,0.010744518,-0.03602819,0.01537314,0.012252643,0.00033489746,0.015345341,-0.04075411,0.020404855,0.015331441,0.030301487,0.026145458,-0.02600646,-0.0014169073,0.0045625977,0.014372356,-0.059490994,0.0052054618,-0.013642619,0.012447239,-0.02597866,-0.014261158,0.008478857,-0.025102975,0.020404855,0.02059945,-0.002621843,-0.01303798,0.011710552,0.010313625,0.0020554278,-0.011029463,-0.038780343,-0.018736882,-0.026340054,0.013253425,0.016971612,0.05262451,-0.069332026,-0.009347592,-0.010793167,-0.008367659,0.033887625,-0.025645066,-0.008583104,-0.038224354,0.00077230565,0.012579287,0.042116288,0.0065224646,0.019167775,0.0017565828,-0.007429424,-0.040448315,0.0018156568,0.0066649374,-0.0081452625,-0.0473982,-0.007742169,0.0011302247,0.021002544,-0.018778581,-0.015790133,-0.005076889,0.016165426,-0.06794205,-0.015484338,0.0023577476,0.012766934,-0.002474158,-0.009799334,0.06916523,0.018667383,0.0025975185,-0.048537977,-0.035555597,0.011536805,-0.0030284112,-0.022323022,0.043839857,0.025353171,0.018528387,-0.0009034847,0.0002404225,0.017458104,0.046230618,-0.048287783,-0.032330852,0.0075475723,-0.05673884,-0.03611159,0.019112177,0.017166208,0.012780834,-0.028244322,0.043784257,0.029328503,-0.022058927,0.021489035,0.011453406,-0.009111295,-0.028105324,-0.050400548,0.007318226,-0.00236296,-0.004305452,-0.034554817,0.008319009,-0.018820282,-0.0149700465,0.013885865,0.031052073,0.008888899,-0.022545418,-0.041532498,0.00235601,-0.03246985,0.005066464,-0.004489624,0.012780834,0.011161511,-0.011536805,0.010584671,0.008409358,-0.034332417,0.023393303,-0.0013091841,0.005320135,0.004465299,-0.019960063,-0.010348375,0.0149561465,0.010077329,-0.026743148,0.035249803,-0.011481206,0.034777213,-0.045090836,-0.0036869126,-0.018083595,-0.013899765,-0.045229834,-0.00036617194,0.014115211,-0.028689114,0.011279659,0.0070159063,-0.07528113,-0.014636452,-0.011919049,0.031441268,-0.014427955,0.032747846,0.023921495,0.032303054,-0.011960748,-0.017235707,-0.016777016,-0.027104542,-0.012544538,0.019834964,-0.02721574,-0.03313704,0.032886844,-0.0074780732,-0.02005736,0.023546202,-0.023170907,-0.041671496,-0.009806284,-0.0005729309,-0.003042311,-0.018792482,0.009312842,-0.002898101,0.0177083,0.013531421,0.0002068676,0.009173845,-0.009396241,0.04372866,-0.01829209,-0.020863546,0.009847984,0.010174627,0.016012529,-0.005844851,-0.025784064,-0.0011250122,-0.024116091,-0.014789349,0.019876663,0.004774569,0.013885865,-0.0043332516,0.011522905,0.010786218,-0.0069881068,-0.034137823,0.068664834,0.010077329,-0.004027457,0.051790524,-0.02481108,-0.0033689556,-0.00013215636,0.017527603,0.0042463783,-0.008617854,0.008409358,-0.00942404,0.0024498336,0.023838097,0.000831814,-0.009688136,0.017346906,0.04067071,0.00070106937,-0.00889585,0.009549138,0.067219265,0.0010946065,0.022142325,0.039225135,0.025645066,-0.0028042775,0.006609338,-0.018764682,-0.002149251,0.02064115,0.014928347,-0.0055147316,-0.03141347,0.01831989,0.031079873,-0.0065954383,0.035750195,-0.008478857,-0.027896827,0.037334766,0.0012283917,0.0056398297,0.018027995,-0.02251762,0.007568422,0.021614134,0.014525254,-0.021377837,0.029550899,0.014094361,0.017597102,0.018139193,-0.015776234,0.009973081,-0.013190877,0.029078308,0.024352388,0.020474354,-0.021586334,0.026089858,0.0032942442,-0.023990994,0.027910728,-0.029411903,-0.0236991,0.04831558,-0.009973081,0.012023296,0.0023577476,-0.0115298545,0.00560508,0.038029756,0.016777016,-0.019320672,0.05434808,0.021433437,0.008034064,-0.0035131655,-0.024407987,4.9843686e-05,-0.0067518107,-0.016095927,-0.040364917,-0.022948511,0.028452817,-0.019821065,-0.026256656,-0.013656518,0.017291307,-0.037084572,-0.009382341,-0.0063452427,-0.002621843,0.0080618635,0.0037564114,0.023254307,0.011488155,0.033998825,-0.0014108261,-0.015651135,-0.055321064,-0.02771613,-0.008784651,-0.019139975,-0.029967893,-0.0138511155,-0.024755482,0.02709064,-0.042116288,-0.0047467696,0.00077708374,0.020126859,0.010855717,0.003662588,-0.0031465592,0.015790133,0.020390954,-0.0024307214,-0.001860831,0.013232576,0.028522316,0.0060081733,0.015122944,0.024950078,0.026979443,-0.028147023,-0.010348375,0.034582615,-0.01652682,0.0103692245,-0.0054278583,-0.01587353,0.020974744,-0.021961628,-0.0081313625,0.00011803941,0.0019407546,-0.03358183,-0.007756069,0.049510963,0.0022726115,0.025895262,-0.011335258,-0.009125195,0.0025923061,-0.007568422,0.029856695,-0.011974648,-0.00309791,0.023268206,-0.031107673,-0.018570086,0.02834162,0.018514486,0.021641934,-0.004906617,0.024352388,-0.022767814,-0.0022274372,-0.024602583,-0.026214955,9.0782836e-05,-0.00034467073,0.00502129,-0.028577916,0.028466718,0.019084377,-0.010542971,0.014900547,0.012231793,-0.026479052,0.008840251,0.007922865,-0.00677266,0.015609436,0.027076742,0.009243344,0.016415622,-0.047954187,-0.024922278,0.022934612,0.0176666,-0.016735317,0.0056572044,0.032553248,0.020251958,-0.0020067785,0.0077074193,-0.007825567,-0.016860414,-0.0037286119,0.012009396,-0.011029463,0.015539937,0.025561668,-0.019237274,-0.019709866,0.029912293,-0.028689114,0.022809513,-0.0054834574,-0.019237274,0.0043506264,-0.006494665,-0.0105638215,-0.0049135666,0.010737568,-0.012002447,0.041838292,-0.0001074517,0.014469655,0.0025245447,0.012641836,0.0127321845,0.030607281,0.110197335,-0.019862764,0.018806381,0.0010833129,-0.03246985,0.0352776,-0.01834769,0.024296788,-0.017346906,0.022851214,0.0044687744,-0.049816757,0.014511354,0.0026670173,-0.023865895,-0.0069116578,-0.037668362,-0.025478268,0.018361589,-0.010814017,0.039947923,-0.0138650155,0.033415034,0.005372259,-0.017319107,-0.0047015953,-0.0068386844,-0.010904365,-0.003363743,-0.019278973,0.01299628,0.001831294,0.045118637,-0.0037042873,0.01891758,-0.015261942,0.0076657203,0.020432655,0.036973376,-0.029411903,-0.03594479,-0.009924432,-0.010751468,-0.0020571651,-0.015136844,0.007304326,-0.0025679816,-0.015706735,0.0023542726,-0.004308927,-0.019751566,-0.001151943,-0.0032907692,-0.004896192,0.0018034944,-0.0036313136,0.038641345,0.022628818,-0.0022430746,0.030662881,-0.0128572825,0.00012205731,0.0071722786,0.042227484,0.02251762,0.020933045,0.0077630184,0.0077213193,0.00034010987,0.026145458,0.00885415,0.029912293,-0.023337705,-0.022851214,0.010000881,0.0062236194,0.040420517,-0.043895457,-0.018987078,0.034137823,-0.012037196,-0.01662412,0.009847984,-0.010299725,-0.0031830461,0.010973864,0.0022100627,-0.04011472,0.0065328893,-0.0006654512,0.0074016247,-0.010139878,-0.0066336626,0.010751468,-0.030079091,-0.020168558,-0.008763801,0.013218676,0.04675881,0.029606499,0.004482674,-0.012885082,-0.02244812,0.011932948,0.0056398297,-0.0027591032,0.044673845,0.006251419,-0.028216522,-0.0151090445,-0.006849109,0.010320575,-0.0352776,-0.018750783,0.01948747,-0.01299628,-0.017652702,-0.0031396092,0.013183927,-0.015678935,0.0025349695,0.037001174,0.018208692,-0.015748434,-0.0034627789,-0.00502824,0.013302075,0.016735317,0.007262627,-0.004593872,0.008089663,0.020543853,0.004010082,0.007735219,0.03169146,0.033609632,-0.0061054714,-0.015637236,0.0021075518,0.001467294,0.0072973766,0.028119223,0.017611003,0.03169146,-0.00501434,0.0076170713,-0.013941464,0.0036104638,0.004079581,0.038808145,-0.016916014,0.028494518,-0.026131557,-0.016902113,-0.01597083,0.030245887,-0.027479835,0.04197729,-0.005274961,-0.03077408,-0.022920713,-0.018403288,-0.04792639,0.01952917,-0.003662588,0.018194793,-0.0050317147,0.009771534,-0.006022073,0.014469655,0.009556089,0.046925604,0.00885415,0.019348472,0.008360708,-0.03135787,0.0057857772,-0.020377055,-0.03141347,-0.017458104,-0.051123336,-0.00022826019,-0.027340837,-0.02779953,-0.00089392863,0.0177917,-0.0057996768,-0.0032733947,0.020293657,-0.010125979,0.00829816,0.020001762,-0.009542189,0.03416562,0.008652603,-0.00068934145,-0.022114526,0.014108261,0.002461996,0.01659632,-0.011057263,-0.0060463976,-0.03955873,-0.0062270947,-0.0015211555,-0.02004346,0.012259592,0.017402506,0.008944498,-0.020029562,-0.009868833,-0.018806381,0.005320135,-0.01298933,0.0066475626,0.0074155247,0.032247454,0.0058796005,-0.0061714957,0.01649902,-0.003787686,0.0036382633,0.004791944,0.007050656,-0.01239164,0.04075411,0.045674626,-0.0071236296,0.048176583,0.020543853,-0.011307458,0.019626468,-0.0103970235,-0.000119668286,0.0014837999,-0.024977878,0.0035861393,0.0103970235,0.038196553,-0.040364917,0.0060950466,0.006963782,-0.006042923,0.0002684392,-0.03133007,0.042922474,-0.020891346,-0.010223277,0.0071236296,-0.021183241,-0.0295231,0.0063973665,0.015289742,0.018695183,-0.02425509,-0.016207125,-0.019126076,-0.021516835,-0.008555305,0.0018000195,0.018639585,-0.015456539,0.010383124,0.011648003,0.007908966,-0.014622552,-0.0026374804,0.022545418,0.05621065,-0.008902799,0.021641934,-0.027285239,0.014636452,-0.009430991,-0.016610218,0.010876566,0.0076587703,0.015150744,-0.013107478,0.0067518107,-0.0037008123,-0.011265759,-0.013420222,-0.017402506,-0.036250588,-0.0051985118,0.0064008418,0.025658965,-0.00384676,0.028772512,-0.0176666,0.015428739,-0.019223375,-0.009597788,0.049955755,0.034471415,0.007811668,0.020293657,0.016804816,-0.01120321,-0.0029154758,0.024380187,-0.0018660434,0.0005507782,0.0016949025,0.0035079531,0.031024275,-0.006296593,0.027632732,-0.01827819,0.003396755,0.03180266,0.0116132535,0.008534456,0.021892129,-0.025061276,-0.013107478,0.00709583,0.0074780732,0.017833399,-0.01473375,-0.02604816,0.027354738,0.041421298,0.02709064,-0.0026739673,-0.0116688525,0.015776234,0.031608064,0.015526037,0.051067736,-0.030913077,0.012516738,0.005486932,0.026159357,0.0001261838,-0.035666797,0.04492404,0.0036278386,0.026618049,0.00016136758,0.0045069987,0.0355834,-0.013899765,-0.039947923,-0.001066807,-0.0006489453,-0.009396241,-0.004899667,0.030218089,-0.0065259393,0.030357085,-0.03905834,0.0075406223,0.026298355,-0.010953015,-0.01061247,-0.010417874,-0.000375728,-0.008951449,-0.021767031,0.031191071,0.008339859,0.006067247,-0.035249803,0.0044583497,-0.010188527,-0.02065505,-0.007422474,0.011383907,-0.0010364013,0.015817933,0.0115993535,-0.022045027,-0.0018104444,0.026103757,-0.007895066,-0.012064996,0.026729247,0.044701643,0.016457321,-0.0006267925,-0.029967893,-0.0004482674,-0.004138655,-0.04781519,-0.02659025,-0.020126859,-0.015275842]",
      "faculty": "NUS Business School",
      "module_code": "DMB1204DO",
      "module_credit": 4.0,
      "preclusion": null,
      "prerequisite_rule": null,
      "prerequisite_tree": null,
      "review_summary": "",
      "sentiment_tags": [],
      "title": "Design Your Own Course",
      "updated_at": "2026-01-17T19:10:49.772671+00:00",
      "workload": [
        0,
        0,
        0,
        0,
        0
      ]
    },
    {
      "attributes": {},
      "corequisite": null,
      "created_at": "2026-01-15T10:58:18.027673+00:00",
      "department": "Division of Graduate Medical Studies",
      "description": "This compulsory module is an extension of AUD5106 that introduces students to advance methods of diagnostic audiological assessment (objective and subjective tests) and management of adult patients. This module involves lecture in the morning and clinical practicum in the afternoon, whereby students will need to prepare and discuss session plans for cases to be observed on the day with clinical supervisor.",
      "embedding": "[-0.026275897,0.031671617,0.037644554,-0.035787422,-0.056918565,0.0704706,0.02418035,-0.015434267,0.01060949,-0.01143767,0.015208399,-0.084072836,-0.011644715,0.010076192,0.0030178383,0.011795294,0.0011536487,-0.0056341346,0.013828099,0.04587616,0.027104078,0.0047275284,0.051271882,0.01326343,0.02328943,-0.061134756,0.0057721646,0.054609697,0.03628935,-0.033001725,0.022097353,-0.031521037,-0.020478636,0.034055773,-0.079906836,-0.012228206,0.006073321,0.011544329,-0.027731488,-0.020315511,-0.014191996,-0.009724842,-0.008971952,0.016914953,-0.025472814,0.011318462,0.021921678,0.0018116441,0.0038522927,0.002581789,-0.011581974,0.03822177,0.032775857,0.05024293,-0.013388912,0.03495924,-0.014430412,0.03398048,0.020001806,-0.0038366073,0.030391702,9.538581e-05,0.00011548251,0.006123514,-0.0043416717,-0.034181256,0.0019324204,0.03581252,0.0023998402,0.02017748,0.023038466,-0.0038993482,-0.058725502,0.02017748,-0.054007385,0.04479702,0.012686214,-0.01192705,0.0269535,0.0076167476,-0.033754617,0.0245317,-0.049515136,-0.0039401297,-0.014330027,-0.042814404,-0.06504979,0.021607973,-0.010998484,-0.041885838,-0.018006645,-0.011814116,-0.014016322,0.063544005,0.0025347332,0.015773067,-0.0032468427,0.010063644,0.0053957193,-0.014944888,0.03546117,-0.014555894,0.03242451,0.015923645,0.052702375,0.0017520402,0.003883663,0.0029190213,-0.05355565,0.018646602,-0.040229477,0.02758091,0.004570676,-0.013627328,0.0066379895,0.021884033,0.0048247767,-0.087536134,0.004087571,-0.027204463,-0.045424428,0.020202577,-0.03325269,-0.045851067,0.051121302,-0.005022411,-0.023628231,-0.025723778,-0.076895274,-0.026752729,-0.023866646,0.010358526,0.024280736,-0.018370543,-0.0026821743,0.010446363,-0.02183384,0.010847906,-0.03558665,-0.053656038,0.058223575,0.00068309176,0.025924549,0.0026664892,-0.057470683,0.009204093,0.029287463,0.0015810712,-0.008545314,0.030868534,-0.053405073,0.042563442,-0.00017685097,0.009473879,-0.00027213874,0.017943904,-0.037418686,0.0009622889,-0.014756665,-0.028032644,0.056165673,-0.0045549907,0.0026978597,0.0138782915,0.017718036,-0.0047494876,0.0071963836,0.027204463,-0.05837415,0.0070144353,-0.029538427,0.02896121,-0.03372952,0.007152465,0.057671454,-0.043341428,0.0071838354,-0.040681213,-0.03034151,-0.007685763,0.013790455,0.0006650538,0.030190932,0.0066693597,-0.0050820145,-0.03159633,-0.032374315,-0.015911099,-0.00026410006,-0.013250883,0.045575004,-0.033202495,0.05174871,0.06093398,0.028710246,0.0073595103,-0.00573452,0.012290946,-0.010000903,-0.001520683,-0.015208399,-0.018257609,0.011908227,-0.018822277,0.033428364,-0.026903307,0.012623473,0.012623473,0.047607813,-0.02584926,0.057420492,-0.026752729,0.04479702,0.046051838,-0.053254493,0.03478357,-0.00054349325,-0.019775938,0.0056309975,0.0027355042,0.014631183,0.0013167751,0.014568442,-0.010038547,0.015973838,0.031044208,0.0063933,0.0011599228,0.03606348,-0.08507669,-0.015308785,-0.036565408,0.0016547918,0.010860453,-0.02017748,0.0023292566,0.011970968,0.009178997,0.010151481,-0.071876,0.0062803663,0.019750843,0.017165916,0.029212173,-0.012610925,-0.0134516535,0.0018022329,-0.056717794,0.021796197,0.030567378,-0.009856598,0.004282068,0.014229641,-0.008288076,-0.025949646,-0.010515379,0.04946494,-0.022059709,-0.04113295,0.02770639,-0.055061433,-0.032951534,0.008595507,-0.017366687,-0.02197187,-0.02515911,0.022009516,0.00067250425,-0.052752566,-0.00964328,-0.08161339,-0.017341591,0.035536457,0.03834725,0.0034695729,-0.028559668,0.014217093,0.09069828,-0.019637909,0.02238596,-0.01899795,-0.011400025,-0.024004677,-0.048084643,0.012303495,0.03159633,-0.027480524,-0.01879718,0.011958419,0.0028892194,-0.009084885,-0.024293285,0.010891824,-0.07182581,-0.007579103,0.007008161,0.028559668,-0.056165673,0.015258593,0.040656116,0.024757568,0.093760036,0.021545233,-0.009147626,0.0009050378,0.034382027,0.043341428,0.050268028,-0.026752729,-0.03046699,-0.029689005,0.021996967,0.013050112,-0.043592393,0.0025692408,-0.022059709,-0.010753794,-0.034306735,0.052953336,-0.012460347,-0.016563604,0.024682278,0.05169852,-0.042739116,0.040656116,0.04201132,-0.045926355,0.02370352,0.0407565,-0.032775857,-0.03814648,-0.0028076563,0.031521037,0.026150417,0.01810703,0.036866564,-0.0021378968,-0.013727713,0.0061611584,-0.017768228,-0.06971771,-0.0029143158,-0.029839583,0.007202658,0.027355041,0.023716068,-0.027756583,0.012303495,0.046629053,0.04030477,-0.017354138,-0.064798824,0.02135701,-0.00091837026,-0.055663746,-0.021394655,0.03345346,-0.05832396,-0.0207296,0.027129175,-0.00022390667,0.028710246,0.022360865,0.044194706,0.03711753,0.02620061,-0.057470683,-0.021720907,-0.03310211,-0.05977955,0.05797261,-0.025598295,-0.030140739,0.0046553765,-0.051949482,0.024368573,-0.01637538,-0.037468877,0.020403348,-0.03054228,0.030692859,0.002749621,0.03026622,-0.014480605,0.02951333,0.047632907,-0.029036498,0.034658086,-0.026476668,0.0039024854,-0.032324124,-0.037770033,0.0060231285,0.022059709,0.020541377,0.007158739,0.018960306,0.06254015,0.04331633,-0.02652686,-0.022850243,0.012999919,-0.009749939,0.04810974,0.0037299478,0.05285295,-0.029613715,0.006964242,0.019675553,-0.031872388,0.005154167,-0.055864517,0.058223575,0.048536375,0.045073077,-0.00749754,0.04913869,0.02321414,0.023578038,0.0060450877,-0.016387928,-0.015233495,0.01727885,-0.03275076,0.055964902,-0.029638812,0.0103648,0.016413026,0.021934226,0.002344942,-0.020215126,0.03711753,-0.053957194,0.0483607,-0.04941475,-0.017931355,-0.006132925,0.014455508,-0.025108917,-0.012974823,-0.0083131725,0.029663907,-0.046955306,-0.04012909,-0.05977955,0.053957194,-0.010923195,0.057822034,0.0041754083,0.019976709,-0.026476668,0.014129256,-0.04803445,0.019688101,-0.008978226,-0.026853114,0.03736849,0.01215919,-0.05772165,-0.012567007,-0.022448702,0.0105279265,-0.016676538,-0.0057313833,-0.056567214,0.023327075,0.047005497,0.020654311,-0.030366605,0.012215657,0.057822034,0.033077013,0.004304027,0.010433815,-0.015760519,-0.0134892985,0.00476831,0.004140901,-0.010302059,-0.041158043,-0.017655294,0.0050600553,0.019098336,0.0064309444,0.051949482,0.014191996,-0.0067007304,0.013715166,-0.0074473475,-0.026451573,-0.02301337,-0.0016375381,0.014154352,-0.012391332,0.02770639,-0.012949727,-0.020767245,0.025058724,0.015973838,0.017253753,0.020641763,0.017605102,0.0038617037,0.02246125,0.07202658,0.028082836,-0.0083131725,0.0018806591,0.0049345735,0.012554458,-0.050619375,0.016839663,-0.0134516535,-0.0134140095,-0.018345445,-0.0057439315,0.015810711,0.006456041,0.020641763,-0.010816535,-0.006327422,-0.019537523,-0.03227393,0.0056874645,0.017881162,0.008319446,-0.053103916,-0.049966868,-0.014091611,-0.020641763,-0.0043510827,-0.008306898,-0.030818341,0.0039652265,-0.02860986,-0.01631264,0.04437038,0.019449685,-0.017893711,-0.019562619,0.015860906,0.019587716,-0.024958339,-0.035059627,-0.023590587,-0.00857041,-0.0034413396,-0.008884114,-0.00922919,0.0039934595,0.014091611,-0.014518249,0.036791276,0.018069385,0.016852211,0.01838309,-0.027003692,-0.040856887,-0.023076111,-0.04090708,-0.0008587664,-0.010151481,0.0016328325,-0.03558665,-0.0019747706,0.021946775,-0.0021692673,-0.039903227,0.03352875,0.03947659,-0.015384074,-0.027279753,-0.0255732,-0.012535636,-0.011945872,0.021244075,0.00067603344,-0.00062701706,0.010245592,-0.02175855,-0.009442508,-0.011494136,0.001544211,0.02640138,0.00048624215,0.00268688,0.025824163,-0.031897485,-0.0077171335,0.040455345,-0.017027887,0.012636022,0.015936194,0.005401993,0.023665875,-0.00208143,0.024883049,0.018295253,0.0063933,0.014719021,0.013740262,0.025686134,0.00021116242,0.015057821,0.016049128,0.009756213,-0.017981548,0.025723778,0.022925533,0.019437138,0.0190105,0.044746824,0.006274092,-0.03947659,-0.0252344,-0.004015419,-0.011205529,-0.025083821,0.00034291836,0.01267994,-0.0031950814,-0.023753712,0.027430331,0.025824163,0.0099318875,-0.01852112,-0.005122796,-0.012422702,0.017542362,-0.029538427,-0.0038585667,-0.023051014,0.032123353,-0.04863676,0.006951694,-0.05174871,-0.03736849,0.025535556,0.012541911,-0.038271964,0.013225786,0.06660576,-0.007623022,-0.032449603,0.055814322,-0.009034692,0.021093497,-0.03054228,-0.017881162,-0.026627246,-0.042186994,-0.019110885,-0.00653133,0.015672682,-0.004693021,0.028258512,-0.0088527445,-0.019939065,0.017379235,-0.0035856436,-0.033403266,-0.024205448,0.027104078,-0.04429509,0.050142545,0.014944888,-0.0007560281,0.025246946,-0.005260826,-0.0010697327,-0.03586271,-0.0031182237,0.03352875,0.012341139,0.042538345,-0.038297057,-0.015773067,0.0007928884,0.0017598829,-0.0017598829,0.004347946,-0.020001806,-0.0015622489,-0.027882066,0.0074598957,-0.020917824,0.038548023,0.0056341346,-0.0047306656,0.00092307583,0.02888592,0.015434267,0.02321414,0.0013497141,-0.020164933,0.040204383,0.017943904,-0.006208214,0.0015426424,-0.0594282,0.028434185,-0.01879718,0.005110248,0.00031390067,-0.021871485,0.04851128,-0.015722875,0.025924549,0.014480605,-0.00981268,-0.00024429747,-0.015534652,-0.020930372,0.022699665,0.008193964,-0.019876324,-0.004235012,-0.02301337,0.022511443,-0.02384155,-0.022298124,0.04690511,0.03054228,-0.010019725,-0.02184639,0.022160094,-0.03862331,0.048536375,-0.0018634053,0.009197819,-0.00086347194,0.015371526,0.022197738,-0.010659683,-0.028685149,0.018483475,-0.005897647,0.031746905,0.011770197,-0.035787422,0.012196835,0.003613877,-0.018596409,-0.0045267576,0.013426557,0.034532603,-0.0023214142,0.04477192,-0.03676618,-0.00046820412,-0.003811511,0.009831502,-0.030391702,-0.010985935,-0.014769213,-0.020365704,-0.011757649,0.011889405,0.010007177,0.009793858,0.03834725,0.021256624,0.026024934,0.017191013,-0.01810703,-0.035636842,-0.012698762,0.0010469891,-0.014969984,0.018019192,0.015961291,-0.02652686,0.007428525,0.0126172,0.052200448,0.019161077,0.011945872,0.0067760195,-0.004335398,0.008470024,0.025171658,-0.0217711,0.007980646,-0.026050031,-0.017429428,-0.019562619,0.015635038,0.027380139,-0.015283689,-0.030065449,0.014731568,-0.020240221,-0.0062333103,0.0067258268,0.03684147,0.009662102,0.030692859,-0.057169527,-0.010007177,0.0105279265,0.016839663,0.027932258,0.01609932,0.0033221317,0.02612532,-0.022749858,-0.034306735,0.013602232,0.008720988,0.0040687486,-0.0071838354,0.016187157,0.0020924096,-0.014932339,0.020302963,0.021984419,-0.0036923033,0.026024934,-0.03290134,-0.011958419,0.029739197,-0.00463028,0.019801036,0.0035072176,0.026752729,0.031872388,-0.012391332,-0.0035699585,0.009248012,-0.007986919,0.04567539,0.025874356,-0.01185176,-0.0075226366,0.027982451,0.013351268,-0.036941856,0.02494579,0.014342574,-0.05641664,-0.0067258268,0.025046175,-0.003538588,0.025309687,-0.00033174263,-0.020993112,-0.011450218,-0.008419831,-0.015860906,0.0016187158,0.026150417,0.020817438,-0.0105467485,0.014706472,-0.016362833,0.03305192,-0.010182852,0.011544329,0.02515911,0.071976386,-0.0034883951,-0.06620422,0.026175512,-0.032851145,0.028810631,-0.023189045,0.025297139,-0.018621506,-0.010985935,-0.04479702,0.00017851753,0.0010971818,0.025472814,-0.0089845,-0.021934226,-0.005853728,0.010214222,0.020955468,-0.00705208,-0.039075047,-0.0068952274,0.0051824,-0.005122796,-0.01198979,0.023176497,0.015936194,-0.010233045,-0.0025708093,0.02046609,0.011619619,-0.018496023,0.023816453,0.0030382292,-0.0082755275,-0.020164933,0.018207416,-0.004075023,-0.023916839,-0.0040530637,-0.010201674,-0.039702456,-0.012843067,-0.02460699,0.013313623,-0.043492008,0.02267457,-0.017153367,0.018207416,0.0061015547,-0.03751907,-0.016626345,0.0042977533,0.03345346,-0.019311655,0.031470846,-0.010847906,0.0070269834,0.02820832,0.011117691,-0.070018865,-0.035536457,-0.014468056,-0.019813582,-0.014217093,-0.0050098626,0.003097833,0.012937178,0.018809728,0.0039401297,0.0032374316,-0.015434267,0.018496023,0.005477282,0.023088658,0.03967736,0.01790626,0.025974741,0.019148529,-0.0078049707,0.01887247,-0.020767245,-0.007428525,0.009141352,-0.007867712,0.005662368,-0.0283338,0.02046609,0.01589855,0.036439925,0.003121361,-0.0039809113,0.010107563,0.050895434,-0.0052106334,0.027455427,0.036565408,-0.0054302267,0.03157123,0.031746905,-0.027656198,0.01116161,0.028660053,-0.023603134,0.005866276,-0.03227393,0.037895516,-0.010640861,0.0039024854,0.043868452,-0.022712214,-0.009574264,-0.02079234,0.031947676,0.0030099957,-0.010044822,0.02652686,-0.039702456,-0.0105279265,0.019462233,-0.0010069918,0.016626345,0.04898811,0.0015959722,-0.01582326,-0.0379959,0.0032813502,0.0055682566,-0.0049220254,0.020051999,0.0058098095,-0.0023370993,-0.040957272,-0.022787502,0.020629214,0.0009489564,-0.0025708093,0.00476831,-0.0214323,0.011958419,-0.005991758,0.008137497,-0.004235012,-0.021181336,0.052501604,-0.039978515,-0.0009371925,0.019386945,0.002762169,0.021018209,-0.024217995,-0.0028703972,-0.01699024,-0.01485705,-0.018985404,0.0028154987,-0.04740704,0.021281721,-0.0067634713,0.0027668746,-0.05245141,0.025698682,0.012912082,0.037970807,0.00094660366,-0.03164652,0.007949275,0.0504688,0.05646683,0.026853114,0.013552039,-0.011092595,-0.027179368,-0.020942919,-0.002555124,0.007961823,-0.0065187817,0.010000903,-0.014355123,0.004090708,-0.0101954,0.007754778,0.03608858,0.0077296817,0.030843437,0.013037563,-0.0044169608,0.008407284,0.0013457928,-0.00065681903,0.03164652,0.031822197,0.007491266,-0.0047369394,0.00021841683,0.000851708,-0.00426952,0.010477734,-0.028007546,0.024958339,-0.017567458,-0.028484378,0.025824163,-0.013727713,-0.028860824,0.021256624,-0.027957354,-0.034080867,0.019750843,-0.001874385,0.012711311,-0.017630199,0.030868534,-0.010164029,0.018470928,-0.0029441176,-0.00037428882,-0.011494136,0.004304027,0.029839583,0.0024578755,-0.02135701,0.028685149,-0.008344542,-0.01810703,0.006004306,-0.02088018,0.030416798,0.015597393,0.051246785,-0.007340688,0.010302059,-0.004376179,-0.0061391992,0.010904372,0.0004960454,0.05917724,0.008545314,0.021545233,0.007290495,0.03543607,0.044872306,0.028584763,0.0028625545,0.019261463,-0.0013897114,-0.019299107,0.014806857,0.016124416,0.043592393,0.0074598957,-0.017793326,-0.006189392,-0.0029786252,-0.019537523,-0.024167802,0.040831793,-0.0013136381,0.004222464,-0.0145307975,0.01044009,0.008055935,-0.014982532,-0.018069385,-0.0053298413,-0.0032844872,0.016689084,-0.013326172,-0.019926516,-0.043341428,0.0033848728,-0.013602232,0.026050031,0.038246866,-0.0074536214,0.016249899,0.0025049313,0.033327978,-0.029187076,-0.009040967,-8.313172e-05,-0.015973838,-0.006813664,0.0122595765,-0.015798165,-0.054509312,-0.03877389,0.016174609,0.08201493,0.01852112,0.0070332573,-0.02280005,0.027530717,-0.014932339,-0.025297139,0.04484721,-0.006220762,-0.0039307186,-0.02149504,0.020704504,-0.047356848,-0.039752647,-0.037845325,-0.005671779,-0.015860906,-0.008118675,0.041358814,-0.033327978,-0.011506685,-0.010051096,0.020277865,-0.010044822,0.018370543,0.018634053,0.02267457,0.011826663,0.0060450877,0.0040624747,0.00873981,0.02702879,-0.008639425,0.046679247,-0.01375281,-0.015747972,0.01485705,-0.01499508,-0.00680739,0.00037801405,-0.0146437315,0.03089363,0.004012282,-0.011977242,-0.010176578,0.013777906,0.0013473612,0.013677521,0.005220045,0.035636842,0.014468056,0.011538056,0.018357994,-0.009109981,-0.010201674,-0.009072337,-0.0037832775,0.025874356,0.002009278,-0.018094482,-0.03282605,0.028835727,0.0101954,0.0069705164,0.018207416,-0.023866646,0.0025927685,-0.0030162698,-0.024381122,0.02218519,0.004849873,0.017153367,0.028158126,-0.007666941,0.012711311,-0.003337817,0.014179449,-0.047181174,0.023189045,-0.009329575,0.009147626,-0.023628231,0.02370352,-0.033227593,-0.0100259995,0.018357994,0.007547733,-0.0017881163,-0.005317293,0.003133909,-0.00860178,0.004423235,0.014668828,0.022285575,0.026677439,0.021595426,-0.0034256543,0.012567007,0.031044208,0.007127369,0.02183384,-0.008488847,-0.017818421,-0.0032248835,-0.03435693,-0.0023276883,0.013765358,-0.026451573,0.032449603,-0.03262528,0.023264334,-0.02482031,-0.036741085,-0.013112852,-0.0025237536,-0.010421267,-0.023490202,-0.009743665,-0.023653327,-0.0037550442,-0.008124949,0.0075226366,0.008670796,0.0016124417,0.006481137,0.017893711,0.034883954,0.012039983,0.00018537982,0.023490202,-0.012937178,0.001310501,-0.004272657,-0.015760519,0.007955549,0.050368413,-0.01306266,-0.04070631,0.003202924,0.023904292,-0.006600345,0.0035166286,0.0014532366,0.027053885,-0.0028264786,0.014016322,-0.0038679778,-0.027430331,0.012937178,0.042412862,0.006415259,0.013250883,-0.027279753,0.014330027,0.0051824,0.023515297,-0.0073281396,-0.022197738,-0.013664973,0.0063619292,-0.007309317,-0.004928299,-0.040254574,0.01852112,0.013803002,0.003406832,0.031772003,-0.002443759,0.014053967,0.02135701,-0.009956984,-0.0067007304,0.009900518,-0.03337817,-0.020139836,0.010741246,0.013978677,-0.0011748237,0.0070332573,0.035712134,-0.0062897773,0.010603216,-0.013175594,0.0017238068,0.001631264,0.025171658,-0.007346962,-0.0028327527,-0.02149504,-0.018408187,0.019299107,-0.017554909,0.037468877,-0.00040742385,0.014907243,-0.0071838354,0.022160094,-0.008990774,-0.04740704,0.008702165,-0.05385681,-0.00774223,-0.0013442242,0.030316412,0.0297141,-0.0128179705,-0.0036891662,-0.0133387195,-0.026075127,0.00035899572,-0.009040967,-0.048210125,0.04158468,0.0036640698,-0.015459363,0.057269912,0.021306816,0.0048592845,-0.018696794,0.023540394,0.036615603,-0.010057369,0.028007546,1.9067358e-05,0.021394655,0.035536457,0.021382106,-0.01548446,0.010910646,-0.00030213676,-0.008181416,-0.013163045,-0.011964694,0.0009285656,-0.027856968,0.0018634053,-0.009624457,0.020779794,0.0049345735,0.040003613,-0.020855082,-0.016500862,0.0093734935,-0.0072653987,0.012623473,0.026577054,0.0016532233,0.029939968,-0.051798906,0.00860178,-0.017504716,0.0037205366,-0.007484992,-0.04394374,-0.023603134,0.004962807,0.0007164229,-0.026702536,-0.012987371,0.008062208,0.0023700383,-0.038271964,-0.013978677,0.0024672868,0.051798906,-0.00045800873,-0.024569346,-0.0032938984,0.0111804325,-0.021796197,0.004843599,0.014944888,-0.011362381,-0.028484378,-0.006079595,0.046001643,0.023653327,0.028810631,0.0015904823,-0.012541911,0.026853114,0.013928484,-0.02246125,-0.020415897,-0.010107563,0.017316494,-0.0046741986,-0.0005168283,-0.0037832775,0.008557862,0.005078878,-0.0017818422,-0.0104714595,0.015522104,0.029187076,0.014555894,0.004432646,0.014693924,0.00884647,0.010571845,-0.026275897,-0.009844051,-0.007472444,0.026928404,0.026627246,0.043090466,-0.006004306,0.032399412,-0.03834725,-0.028559668,-0.009279382,-0.0033629134,-0.010847906,0.002749621,0.014204545,0.024443863,-0.030818341,-0.010829083,0.018182319,0.038874276,-0.010791439,-0.008946856,-0.00084072835,-0.0006478,0.08070992,0.001583424,-0.012284673,0.018721892,-0.005260826,-0.020604119,0.023452556,-0.013677521,0.02405487,-0.00895313,0.014969984,0.036414832,-0.054358736,0.021244075,0.0053957193,0.016463218,-0.0037926887,-0.001868111,0.015597393,-0.011236899,0.008990774,0.020691955,-0.015396622,0.007899082,0.010703601,-0.024669731,-0.021344462,0.00070818816,-0.019876324,0.0048122285,-0.006619167,0.0015755814,-0.0047243913,0.022448702,0.025698682,0.0062270365,-0.005348664,-0.024958339,0.034482412,0.0047902693,-0.0031386146,0.039024852,-0.031295173,0.012560733,0.0019386945,-0.0006905423,-0.0504437,-0.02079234,0.041685067,-0.0044389204,-0.0027135448,-0.0062803663,-0.02715427,0.026225705,-0.009367219,0.0074473475,0.009323301,-0.002167699,0.008507669,0.00087131455,-0.04901321,-0.020553926,0.019198721,-0.044069223,-0.0012618768]",
      "faculty": "Yong Loo Lin Sch of Medicine",
      "module_code": "AUD5112",
      "module_credit": 4.0,
      "preclusion": null,
      "prerequisite_rule": null,
      "prerequisite_tree": null,
      "review_summary": "",
      "sentiment_tags": [],
      "title": "Clinical Audiology A - Part 2",
      "updated_at": "2026-01-17T17:08:24.871622+00:00",
      "workload": [
        27,
        9,
        44,
        0,
        20
      ]
    },
    {
      "attributes": {},
      "corequisite": null,
      "created_at": "2026-01-15T10:58:19.653484+00:00",
      "department": "Accounting",
      "description": "The primary objective of the course is to discuss how to conduct rigorous empirical accounting research. We will discuss a select number of research topics that are of interest to financial accounting researchers. The purpose of the course is not to survey all the papers in the selected research topics or the entire financial accounting research area. Students are encouraged to read relevant survey papers for a thorough overview of relevant literatures.",
      "embedding": "[0.018919764,-0.005047226,0.041572288,-0.004026049,-0.034000117,-0.0012724715,-0.01030242,-0.0004156029,0.03459736,0.022524545,0.0012651392,-0.043278694,-0.0048792516,0.012286115,0.011304933,0.040441796,0.025169471,0.012659391,0.022375233,-0.0031275202,-0.008260066,-0.020455528,-0.013064662,0.020391539,-0.037668888,-0.058785647,0.009913146,-0.001438446,-0.014717742,-0.06539797,0.023036465,-0.015869565,-0.06330762,-0.0015237662,-0.041017707,-0.008899968,-0.044195887,-0.0067349668,0.008654673,-0.016978728,-0.008521359,-0.053367812,-0.033274896,-0.017810602,-0.095302716,-0.008803982,0.022289913,0.00050592236,0.020892795,0.026811887,-0.04182825,0.04876052,0.019026414,-0.06288102,-0.017181365,0.023313757,-0.036773026,0.027131837,-0.0051378785,0.010963651,0.030843267,-0.005620471,-0.017010724,-0.00035194602,-0.040377807,-0.013779219,-0.06275304,0.05234397,0.0029142196,0.033744156,0.021564692,-0.015421634,-0.013267298,0.040911056,0.0015250994,-0.021106096,-0.019580996,-0.046627514,-0.04291608,-0.008681335,0.009987801,0.04880318,-0.0046419543,0.021212745,-0.020786144,-0.031931102,-0.056951262,0.0016770761,-0.03922598,-0.009865154,-0.018727794,0.0056951265,-0.01577358,0.008292061,0.06471541,-0.012115475,-0.008126753,0.0005212534,0.015506954,0.0072522205,-0.036090463,0.0032421693,-0.00082054076,-0.0023823013,0.043854605,0.0043619974,0.006740299,-0.05311185,-0.054604955,0.033189576,-0.082504675,0.04144431,0.02073282,-0.0070229224,-0.02487085,0.014675082,-0.08613078,-0.030182036,-0.026705237,-0.03517327,-0.015218998,0.04210554,-0.00023446402,0.0041780258,0.046926133,-0.0048205936,-0.018653138,-0.032976273,0.014728407,0.0123821,0.057505846,-0.008169414,0.034064107,0.0045459694,-0.02843297,0.0044766464,-0.030374007,0.051234808,-0.017106708,-0.06979196,0.047736675,0.019367695,0.0015597607,-0.0039273975,-0.040612437,-0.014120501,0.010883664,-0.0016317497,0.0208608,0.008110756,-0.022332573,-0.0066976394,-0.04603027,-0.022673855,0.05008298,-0.014675082,-0.032698985,0.020114247,-0.026619917,-0.019037079,0.058615007,0.054007713,-0.011688873,0.04504909,0.010169107,-0.00047692683,-0.038948692,-0.0003896069,-0.05272791,0.03873539,-0.04496377,-0.017927917,0.0121687995,0.018631808,-0.01566693,-0.0051005506,0.018151881,0.0016997393,0.005524486,-0.008617344,-0.013128652,-0.014867052,-0.0042793434,-0.006622984,0.016328162,0.0072735506,0.0071135755,-0.016093532,0.019239714,-0.008393379,0.040932387,0.021927303,0.051106825,0.041892238,0.0009231917,0.0068469495,-0.0125420755,0.05149077,-0.018151881,0.009267911,-0.009577197,0.0030182037,0.027430458,-0.02463622,0.0045566345,-0.0047806,0.07192496,0.016413482,-0.019751636,-0.024742872,0.0627957,-0.057505846,0.018237201,0.029840754,-0.037903517,-0.022268584,0.023420407,0.013309958,0.02821967,0.03116322,0.021991292,-0.07495383,-0.015464294,0.0027169166,0.020060923,0.00780147,0.018759789,-0.01405651,0.04161495,-0.06360624,0.013352619,-0.008873305,-0.009859821,0.039439283,-0.0057911114,-0.01969831,-0.015155008,-0.0047352733,-0.0056044734,-0.008638674,0.007380201,0.04231884,-0.016018875,0.014984367,0.04223352,0.020071587,-0.0057911114,-0.04999766,0.0008138751,0.061131954,0.006425681,0.0017384,0.024294939,-0.028966222,0.018599814,-0.042468153,0.00019130399,0.008398712,0.019794296,-0.006569659,-0.03470401,0.016445477,0.03126987,0.004159362,-0.009214587,-0.07388733,-0.005351179,0.003487465,-0.023591047,-0.032272384,-0.039801892,0.04603027,-0.0069909273,0.001361791,-0.04496377,0.023889668,0.03521593,0.022353904,-0.001025176,0.0115182325,0.039951205,-0.008142751,0.04521973,0.013011337,0.018770454,0.021308731,-0.023100456,-0.009433219,0.0010425068,0.056567322,0.0066976394,-0.050210964,0.01729868,-0.040399134,0.047395397,-0.081864774,0.06654979,0.0013164647,0.0193357,0.030459328,0.03939662,0.033744156,0.008942628,-0.007369536,0.003196843,-0.022161933,0.0193357,0.018834444,0.0095878625,-0.016786758,0.05934023,0.01409917,0.015485624,-0.0044099903,-0.018951759,-0.00351946,-0.0077481447,0.0010411736,0.015976215,0.014280476,-0.026470605,-0.03152583,0.036730364,-0.023889668,0.03203775,0.0078921225,-0.021447375,0.04251081,0.011432913,-0.011443578,-0.0038767385,0.014579097,0.0072735506,0.00856402,-0.022631194,0.02081814,0.009118601,-0.018599814,-0.016274836,-0.0059030945,-0.018109221,-0.043662634,-0.004959239,0.0210741,-0.0052738576,0.017234689,-0.005207201,0.0060524046,0.012616731,0.04918712,0.03180312,-0.017277349,-0.023399077,-0.010099784,-0.03939662,-0.029734105,0.0014877717,-0.08224872,0.052088007,-0.004575298,-0.021148756,-0.011251607,0.024742872,0.016626783,0.05255727,-0.013117988,-0.027387798,-0.04170027,-0.010126446,-0.062113136,-0.014408456,-0.020338213,-0.034405388,-0.013800549,-0.023079125,0.010627703,-0.009443885,-0.014547101,0.00044459847,0.03843677,0.03453337,0.0032208392,0.007940115,-0.04543303,0.10042193,0.036943667,-0.02834765,-0.019911611,0.025852034,0.03120588,-0.0077588097,0.050594904,-0.0038340786,-0.006798957,0.037007656,-0.01746932,0.006313698,0.039268643,0.05588476,0.010531718,-0.042553473,-0.009070609,0.030971248,-0.014984367,0.001635749,0.035514552,-0.003279497,0.036303762,0.01388587,0.0044473177,-0.02137272,-0.015240328,-0.0012204794,0.04152963,-0.0022023288,-0.025894694,0.054306336,0.014045845,-0.0425748,0.012158135,0.04298007,-0.032634992,0.017010724,0.011646213,0.020274224,0.027430458,0.027366469,-0.023996318,-0.03402145,-0.026769226,0.030971248,0.028624943,0.036218442,0.021532696,-0.071839646,-0.029968735,-0.021703336,-0.02753711,-0.023399077,-0.00154243,-0.018354518,0.040868398,-0.03856475,0.0015864233,-0.03555721,0.035855833,-0.06654979,-0.018439837,-0.016178852,0.028368982,-0.01907974,-0.043555986,0.023655038,-0.033168245,-0.014589761,-0.016850749,0.070730485,0.021756662,0.023676367,0.02446558,0.029776765,-0.017639961,0.021020776,0.061601218,0.029222183,0.02772908,0.017224025,0.007881458,0.006756297,-0.036815684,0.009699845,-0.0009118601,0.04603027,-0.051789388,-0.01577358,-0.0084733665,-0.051618747,-0.04521973,-0.018322522,-0.028816912,0.019367695,-0.0031408514,0.02777174,0.021490036,-0.039993864,-0.015336314,-0.021799322,-0.023548387,-0.01925038,0.018279862,-0.025404103,0.0046846145,-0.023569718,-0.0070655826,0.0060097445,-0.032741643,-0.02487085,-0.055202197,0.021863313,0.021788657,0.047182094,0.00031278536,-0.014707077,0.053239834,0.0074548563,0.007657492,0.011582223,-0.015293654,-0.011219612,0.03882071,-0.033125583,0.008398712,-0.016445477,-0.0012078147,0.004095372,-0.0021903305,-0.027259817,-0.037796866,0.01757597,-0.034405388,-0.008809315,-0.033680167,-0.0069162725,-0.002948881,0.005721789,-0.005775114,-0.023825679,-0.08412576,0.0015597607,-0.0059457547,-0.013875205,-0.026193315,-0.048035298,0.020039592,-0.04274544,-0.029435484,0.008692,0.013501928,-0.005556481,0.018663803,0.027046517,-0.011678209,-0.009017283,-0.014387126,-0.019932942,-0.006782959,0.0012004825,-0.004564633,-0.019719642,0.017895922,-0.007668157,-0.029862085,0.013853875,-0.006622984,0.016541462,0.021969963,-0.0008658672,-0.052983873,0.032400362,-0.02804903,-0.035919823,-0.009715843,-0.006324363,0.008276064,0.023740359,0.010787678,-0.030395336,2.1580023e-05,0.032634992,0.016573457,-0.008105423,0.004876585,-0.0051698736,-0.04884584,-0.0016090865,0.043342683,-0.019580996,0.009993133,0.018599814,0.0066603115,-0.011571558,0.01965565,-0.009049279,0.029862085,-0.007556174,-0.0040740417,0.024337599,0.043769285,0.0038794049,-0.02843297,-0.001954367,0.005556481,-0.01030242,0.009742505,0.008169414,0.028880902,0.011304933,0.0050338944,-0.022012623,0.00023196441,0.043491993,0.016968064,-0.015954886,-0.026193315,-0.033701498,0.027643759,-0.020658163,-0.004481979,0.022972476,0.0010678362,0.010393072,0.048077956,0.00875599,0.0025476092,-0.03229371,0.0061003976,-0.029456815,-0.044366527,0.0087986505,-0.003386147,0.025340112,-0.0017730613,0.007534844,-0.017106708,0.043641306,-3.1474337e-05,-0.023036465,-0.0073642037,0.057036582,-0.016168186,-0.018301193,0.043641306,-0.008505362,-0.037284948,-0.013832545,0.03854342,-0.0048179277,-0.026129324,0.01397119,-0.003218173,0.037284948,-0.0021650011,0.019954272,0.02495617,0.024038978,0.0030288687,0.023676367,-0.031184549,-0.050296284,-0.0014211154,0.0110063115,-0.023783019,0.023761688,-0.01588023,0.008883971,0.0278144,0.02079681,-0.026918536,0.014472446,0.032826964,0.0034608024,0.03126987,0.027217157,-0.030224696,-0.018354518,0.019591661,0.027878389,-0.014781732,0.015027028,0.039119333,-0.088903695,-0.01922905,-0.040484454,0.011635548,-0.0037647558,-0.011155622,0.016882744,-0.0097745005,-0.010185104,0.018269198,0.04135899,-0.036474403,0.017522644,-0.037327606,-0.02137272,0.008366716,-0.0020316883,-0.03500263,-0.0068576145,-0.011891509,0.0049245777,0.0058391043,0.025894694,0.018706463,0.0011204948,-0.013651239,0.019218385,-0.022844495,-0.023399077,-0.048120618,-0.012051485,0.012904687,-0.0009845156,-0.019954272,-0.012755376,0.028752923,0.021234076,0.00086386746,0.020626169,-0.035770513,-0.015442964,0.01403518,0.018706463,0.022780506,0.0030315348,0.016050871,0.013736559,-0.009769168,0.015976215,-0.013565918,-0.001003846,0.03922598,0.012766042,-0.008489364,-0.008308059,-0.0035274588,0.025894694,-0.002061017,-0.01407784,0.017064048,0.015528284,0.03884204,0.01397119,0.03762623,-0.013395279,-0.012723382,-0.039759234,0.002576938,0.026961196,-0.03133386,-0.003818081,0.0037327607,0.0077588097,-0.0050392267,0.0142378155,0.0047059446,-0.011870179,0.018151881,-0.011326263,-0.02124474,0.004665951,0.0051272134,-0.013853875,-0.027473118,0.07111442,-0.0143764615,-0.03566386,-0.014088505,-0.013288628,0.010910327,0.0018663803,0.015848236,0.012723382,0.026555926,-0.020306218,-0.025233462,0.028326321,-0.019996932,0.005785779,0.01920772,-0.0104304,0.0008865307,-0.011134292,-0.010083786,0.037476916,0.058017764,0.043214705,0.015165674,0.02762243,0.008835978,-0.010553048,-0.008393379,0.004122034,0.033872135,0.015645599,-0.015965551,0.023057796,0.011112962,-0.00699626,-0.02775041,0.0070975777,-0.012094145,0.032976273,0.0051192148,0.0076308292,0.04854722,-0.016701438,-0.029819425,-0.029008882,0.007524179,0.032997604,0.0560554,0.0067029716,0.009209254,0.029840754,-0.029435484,-0.023889668,0.0051778723,-0.031227209,-0.013800549,-0.0030661963,0.021522032,0.0024449583,0.033744156,-0.03754091,0.016808089,0.049784362,0.032826964,0.009043946,-0.0148883825,0.022759175,-0.035770513,-0.0074868514,-0.014216485,0.033360217,0.022695186,-0.04893116,0.003914066,0.0029648785,-0.026321296,0.027345138,0.021298066,0.023399077,0.011678209,-0.01240343,0.014504441,-0.011208947,-0.02785706,0.017629296,0.058700327,0.015048358,0.043598644,-0.021148756,0.025446763,-0.019453015,-0.029584795,0.030075386,0.036111794,-0.017266685,0.044750467,0.0016197514,0.02804903,0.018343853,-0.0019183723,-0.0045379703,-0.017629296,-0.054050375,-0.039908543,0.0030715289,0.0084733665,0.025894694,-0.015123013,0.004492644,-0.013512594,0.017266685,-0.009886484,-0.027174497,-0.028944893,-0.03478933,-0.018557154,0.053965054,0.033168245,-0.010777013,0.0055831433,0.010526385,-0.022247253,-0.025532084,0.027153168,-0.032187063,0.006852282,0.0066976394,0.010147776,0.038138147,0.029307503,-0.012264785,-0.03212307,0.034554698,0.023292426,0.01236077,0.035365243,-0.0062550404,0.05375175,0.03485332,-0.00964652,-0.050509583,0.036879674,-0.003684768,-0.028283661,-0.00797211,-0.0003836078,0.008521359,-0.0062123802,-0.025894694,0.018589148,0.014867052,-0.029179523,-0.0042126873,0.0074441913,0.02794238,-0.03205908,-0.025382772,0.023569718,0.02446558,0.016648112,0.011720869,-0.0017050718,0.02749445,-0.02813435,-0.004665951,-0.027387798,-0.019719642,0.06424614,-0.03532258,-0.018119887,-0.03493864,-0.012147469,0.02826233,0.03126987,-0.029371494,-0.026406616,-0.044579826,0.008452036,-0.0045486353,0.009353232,-0.0012924684,0.014291141,-0.019730307,0.019815627,-0.0040100515,0.026299965,0.006841617,0.0038660734,-0.0064950036,-0.023953658,0.003663438,0.015805576,-0.020764815,0.057463184,0.01562427,0.0018690466,0.022673855,-0.029158194,-0.0038314122,0.012115475,0.03566386,0.028795583,0.026982527,0.014568431,0.05255727,0.058273725,0.016829418,-0.0034954636,0.01783193,-0.004284676,-0.014632422,-0.0055831433,-0.03203775,-0.0029835422,0.028880902,0.015293654,0.036282435,0.030160706,0.052002687,-0.0039460612,0.014472446,0.015933555,0.007988107,0.002442292,-0.018269198,-0.0027329142,0.014045845,-0.011752863,-0.018503828,-0.011624883,-0.017234689,0.017288014,0.019858288,-0.0051432108,0.048248596,0.026577257,0.0071455706,-0.014909713,0.010931657,0.002154336,0.020295553,-0.024294939,-0.03180312,-0.071370386,0.029435484,0.0012358105,0.030331347,0.011368923,-0.035621203,0.061473235,-0.005497823,0.036453076,0.043939926,-0.0057591163,0.015570944,-0.04470781,-0.004969904,0.009897148,-0.036346424,-0.04509175,-0.0004909247,-0.0554155,0.048248596,-0.03173913,-0.029392824,-0.029627455,0.01407784,-0.019911611,0.028731592,0.01409917,-0.0131926425,0.012467421,0.00037694216,0.0058551016,0.023249766,-0.0010878331,-0.0010931656,-0.037028987,0.002091679,-0.04641421,0.0130753275,-0.0020250226,0.0036794355,0.029115533,-0.0043433337,-0.013149982,0.018663803,-0.009571865,-0.03152583,0.021841982,0.034170758,0.022055283,-0.016541462,-0.004090039,0.0045193066,0.022716515,-0.0029248847,-0.00051592087,0.022737846,-0.009102603,-0.010910327,-0.00045426365,0.012414096,-0.0010425068,0.027217157,-0.0071455706,-0.007593502,-0.004047379,-0.017437324,0.0020956786,0.049784362,-0.02427361,-0.020722155,-0.0117741935,0.018162547,-0.0001362291,0.0086120125,0.036922336,-0.030843267,0.004151363,-0.013779219,-0.008963958,-0.007860128,-0.0049832356,0.054263674,-0.025809374,-0.010835671,0.005073888,-0.0012364769,-0.04547569,0.025062822,-0.011368923,0.016861413,0.015293654,0.040676426,0.012456755,-0.0032421693,-0.023377746,0.0067349668,0.01742666,-0.015112348,0.016370822,0.026897207,-0.008329389,0.025425432,0.028539622,0.0048792516,0.010819674,0.025084151,-0.015869565,-0.021564692,-0.01689341,0.0033781484,0.0104730595,0.019431686,-0.023100456,-0.011112962,-0.030821938,-0.03905534,0.0066976394,-0.046712834,0.011336927,0.029584795,0.015048358,0.022247253,-0.012712716,0.015240328,-0.033317555,0.028283661,0.019580996,-0.016008211,-0.029200854,0.014216485,-0.028475631,0.0060364073,-0.05567146,-0.008105423,0.005228531,0.038223468,0.005113882,-0.006809622,0.03126987,0.0023369747,0.0029942072,-0.0125420755,-0.034064107,0.0028955557,0.029456815,-0.0026329295,0.012808702,-0.040015195,0.008148083,0.0043619974,0.056823283,-0.0075508417,-0.0040207165,0.0032874956,-0.018173212,0.013960524,-0.03491731,0.014205821,-0.0017890589,-0.0106437,0.0026329295,0.016658777,-0.011134292,0.012179465,-0.038948692,-0.027643759,-0.023527058,-0.0060364073,-0.003250168,0.0011658211,0.0056684637,0.032272384,-0.014771068,-0.03453337,0.005297854,-0.0029222183,0.011859514,0.00056091393,-0.010137112,-0.009662517,0.018354518,-0.0023529723,-0.00014031181,0.02757977,-0.006750964,-0.013629909,0.024038978,0.0011198282,0.023015136,0.02414563,0.021639347,0.061046634,-0.026022675,-0.044238545,-0.002359638,-0.0033541522,0.050637566,-0.0029355497,-0.01409917,0.021884643,-0.052088007,-0.032080412,-0.02438026,0.0053965054,0.017671956,0.0052951877,-0.010995646,0.046968795,0.02450824,-0.025425432,0.031227209,0.02480686,-0.0047326074,0.010793011,0.03483199,-0.0005782446,0.026726566,-0.0048179277,-0.005348513,-0.037967507,0.018791784,0.011571558,0.006585656,-0.007582837,0.0062283776,0.009417222,0.010910327,-0.017885257,0.013789885,-0.017117374,0.008766655,-0.0160722,0.0022783172,-0.022396564,-0.003914066,-0.00899062,0.005599141,-0.0061110626,0.0060684024,0.006377688,-0.011987494,-0.011102296,0.038138147,0.028624943,-0.005233864,0.012392766,-0.029542135,0.037498247,0.036964994,-0.011155622,-0.0050285617,0.01952767,-0.008436039,0.014557767,-0.014419121,-0.011816854,-0.0068469495,-0.016509468,0.021426046,0.00089252973,0.033146914,0.016637448,0.008228071,-0.016797423,0.027003856,0.02459356,-0.032101743,-0.05567146,-0.018162547,0.026299965,0.03835145,0.026235975,-0.0130753275,-0.022716515,-0.008830645,0.01927171,0.029350163,-0.034234747,0.0051272134,0.017810602,-0.0023663037,0.020711489,0.008318724,0.020583509,0.013160648,0.003935396,-0.011390253,0.03502396,0.013128652,-0.0064203483,-0.008393379,0.008516027,0.0070015923,-0.009081273,-0.016637448,-0.01223279,0.012552741,-0.009827825,0.0068842773,0.043214705,-0.002247655,0.013384613,-0.002567606,0.046968795,-0.0055618132,0.011571558,-0.023356417,0.016616117,0.017138705,0.022695186,0.02798504,0.023697698,-0.057889786,0.004015384,0.033978786,-0.008921298,0.005897762,0.030374007,-0.0011164953,0.033552185,0.008766655,-0.03186711,0.036943667,0.010638368,0.015634935,-0.037199628,0.0125420755,0.011646213,0.013576584,0.007609499,-0.0014211154,-0.013107322,0.013501928,-0.027195828,-0.001573092,-0.0016024208,0.011059636,-0.0060524046,0.0048205936,-0.0002079681,-0.003951394,0.008062763,0.054263674,0.027131837,0.0062497077,0.035621203,-0.020935455,-0.025980014,0.004266012,0.018823778,-0.0084733665,-0.010478392,0.003684768,-0.0027969042,-0.01598688,0.041231006,-0.0010111782,0.03148317,-0.022972476,0.024294939,0.014621757,-0.029542135,0.04577431,-0.0018610478,-0.017415995,0.058956288,-0.036559723,-0.007700152,-0.012894022,0.017320009,0.0062497077,0.012019489,0.002764909,0.019676981,0.023185777,0.009971803,0.020007597,0.0060577374,0.024166958,-0.030651297,-0.022289913,0.005031228,-0.0069002747,-0.006756297,-0.005233864,-0.009699845,-0.021532696,-0.014536437,0.0028715595,-0.018962424,0.010713023,-0.0049219117,0.007513514,0.014707077,0.03449071,-0.0069376025,-0.0150056975,-0.020092918,-0.04167894,-0.034405388,0.009566532,0.01388587,-0.012734046,-0.015496289,0.00045259722,-0.013299293,-0.003002206,0.0037274281,-0.029243514,0.0142378155,-0.0051805386,-0.0006852282,-0.01388587,0.047736675,0.029158194,-0.0010944988,-0.017991906,-0.0061537228,-0.03112056,-0.003818081,0.009838491,-0.001427781,-0.023505727,-0.025681393,-0.033893466,0.016936067,0.02118075,0.011016976,0.01602954,-0.03513061,0.03188844,-0.0038687398,-0.006542996,-0.0011578223,-0.012467421,-0.026449276,0.016808089,0.00856402,0.012478085,-0.0026102662,-0.005529818,0.027430458,-0.020060923,-0.013789885,0.0060364073,-0.02813435,-0.008414709,-0.0009511874,0.011315597,-0.013245968,0.016797423,-0.008750658,0.019772967,-0.006633649,0.025681393,-0.008260066,-0.00964652,0.044750467,0.01901575,-0.009118601,0.0026875876,-0.020178238,0.0023529723,-0.00030345345,0.017810602,-0.022759175,-0.011155622,0.007588169,0.0071882308,-0.00039094003,0.0074441913,0.007614832,0.002484952,-0.023804348,0.05942555,0.009662517,-0.043897264,-0.010574378,0.012798036,-0.006798957,-0.0050178966,0.013736559,0.0073322086,0.006511001,-0.0024929508,0.022439225,-0.014109835,0.008233404,-0.018834444,0.008238736,-0.006447011,-0.011475572,0.048035298,-0.044537168,-0.01952767,0.044195887,0.03882071,0.039908543,0.0027995706,0.004012718,0.0060790675,-0.0067243017,-0.014728407,-0.002535611,-0.018610477,-0.022225924,-0.009865154,-0.0120301545,0.025788045,-0.046968795,-0.013235303,0.007534844,0.017693285,-0.012798036,0.015453629,-0.0021250073,-0.020338213,-0.019559667,0.0071455706,-0.0005732454,-0.027451789,-0.008297394,0.007588169,0.013256633,-0.016296167,-0.023015136,0.006798957,0.012702052,0.009182591,-0.019911611,-0.00040360476,-0.041892238,0.033616178,-0.01598688,-0.026342625,-0.047779337,-0.014323136,0.021905972,-0.0089372955]",
      "faculty": "NUS Business School",
      "module_code": "BAA6001A",
      "module_credit": 2.0,
      "preclusion": null,
      "prerequisite_rule": null,
      "prerequisite_tree": null,
      "review_summary": "",
      "sentiment_tags": [],
      "title": "Introduction to Empirical Research in Accounting",
      "updated_at": "2026-01-17T17:08:29.375965+00:00",
      "workload": [
        0,
        2,
        0,
        1,
        2
      ]
    }
  ],
  "reviews": [
    {
      "academic_year": "2025/2026",
      "comment": "Taken in AY25/26 sem 1: Under Dr Bertrand Sim Assessments: 4% - Tutorial Participation + Presentation 36% - 3 Assignments (Python, in pairs) 60% - Finals Content: 1. Binomial Tree Method For Vanilla Options 2. Path-Dependent Options (Barrier Options) 3. Similarity Reduction (Lookback and Asian Options) 4. Forward Shooting Grid Method 5. Stochastic Calculus 6. PDE Models For Financial Derivatives 7. Consistency Between BTM and Black-Scholes PDE 8. Introduction To Finite Differences 9. Explicit And Implicit Schemes 10. Upwind Treatment And Iterative Methods 11. Lattice Methods For Lookback And American Options 12. Options With Two Underlying Assets 13. Monte-Carlo Simulation Methods 14. Variance Reduction 15. Flaws In Black-Scholes Model 16. Local Volatility Model 17. Stochastic Volatility Model 18. Jump Diffusion Model One of the, if not the most difficult module I have done in my time at NUS. The content is insanely heavy and it didn&#x27;t help that the tutorials and assignments were extremely hard, especially since some of the key concepts in the lectures needed to solve the questions were not in code so I have gotta figure it our myself alongside my bestfriend ChatGPT. This is the first time this module is carried out in Python and not MATLAB unlike previous years so maybe that&#x27;s why. Perhaps next semester will be better. Strong programming skills in python and understanding of financial derivatives pricings will be extremely helpful for this module. Stuffs from DSA2102/MA2213 are applied quite a lot in QF4102, good to revise contents from there. I have to be frank the tutorials are not very helpful...people just show up to present to get the class part score and questions weren&#x27;t gone thru well, expect a lot of self-study. ATB taking this hellish modul, cheers",
      "disqus_post_id": "6823856576",
      "id": 5494,
      "module_code": "QF4102",
      "rating": null,
      "source": "Disqus",
      "timestamp": "2026-01-15T09:01:31+00:00",
      "user_id": null
    },
    {
      "academic_year": null,
      "comment": "yeah most 4ks have A median actually. dw i can answer i got A-",
      "disqus_post_id": "6823533976",
      "id": 5495,
      "module_code": "MA4207",
      "rating": null,
      "source": "Disqus",
      "timestamp": "2026-01-14T17:33:44+00:00",
      "user_id": null
    },
    {
      "academic_year": null,
      "comment": "@disqus_kr9PF6s7Jt:disqus Median grade is an A? Isn\u2019t that assuring? So despite the finals being too tough, prof moderated and dished out As. Curious did you also get an A despite your midterm below lower quartile? Feel free to ignore if you don\u2019t wish to answer!",
      "disqus_post_id": "6823458966",
      "id": 5496,
      "module_code": "MA4207",
      "rating": null,
      "source": "Disqus",
      "timestamp": "2026-01-14T15:06:45+00:00",
      "user_id": null
    },
    {
      "academic_year": null,
      "comment": "cohort size of 30. my grade ended up being fine. the median grade should be an A because people are cracked af ig. was below lower quartile for midterms lol",
      "disqus_post_id": "6823378104",
      "id": 5497,
      "module_code": "MA4207",
      "rating": null,
      "source": "Disqus",
      "timestamp": "2026-01-14T11:38:27+00:00",
      "user_id": null
    },
    {
      "academic_year": null,
      "comment": "@disqus_kr9PF6s7Jt:disqus may I ask how roughly how big was the cohort? Finals sounded like hell.. was the curve also steep?",
      "disqus_post_id": "6823360896",
      "id": 5498,
      "module_code": "MA4207",
      "rating": null,
      "source": "Disqus",
      "timestamp": "2026-01-14T10:29:49+00:00",
      "user_id": null
    }
  ]
}